parkon_client/__init__.py
parkon_client/parkon_client.py
parkon_client-0.1.0.dist-info/LICENSE
parkon_client-0.1.0.dist-info/METADATA
parkon_client-0.1.0.dist-info/WHEEL
parkon_client-0.1.0.dist-info/entry_points.txt
parkon_client-0.1.0.dist-info/top_level.txt
parkon_client-0.1.0.dist-info/RECORD
