Metadata-Version: 2.1
Name: parkon-client
Version: 0.1.0
Summary: Library and CLI client to request parking spots in the parkon API.
Home-page: https://github.com/SimonRupf/parkon-python-client
Author: Simon Rupf
Author-email: simon@rupf.net
License: UNKNOWN
Project-URL: Bug Tracker, https://github.com/SimonRupf/parkon-python-client/issues
Platform: UNKNOWN
Classifier: Programming Language :: Python :: 3
Classifier: License :: OSI Approved :: GNU Lesser General Public License v3 (LGPLv3)
Classifier: Operating System :: OS Independent
Requires-Python: >=3.6
License-File: LICENSE
